{
   "botToken":"",
   "owner":"",
   "shardCount":1,
   "shardNames":[
      "Clone DueUtil: shard 1"
   ],
   "logChannel": "[serverid]/[channelid]",
   "errorChannel": "[serverid]/[channelid]",
   "feedbackChannel": "[serverid]/[channelid]",
   "bugChannel": "[serverid]/[channelid]",
   "announcementsChannel":"[serverid]/[channelid]",
   "carbonKey":"[https://www.carbonitex.net key you won't have]",
   "discordBotsOrgKey":"https://discordbots.org/ key you also won't have",
   "discordBotsKey": "https://bots.discord.pw/ key you also also won't have",
   "discoinKey":"http://discoin.sidetrip.xyz/ you will never get",
   "sentryAuth": "sentry public dsc token"
}
